{"repo": {"timestamp": 1651623395000, "version": 20001, "name": "Tulip", "icon": "icon.png", "address": "https://dionyzjahoda.github.io/TotallyNotTulip/fdroid/repo", "description": "Repository for the Tulip application, whatever its purpose might be."}, "requests": {"install": [], "uninstall": []}, "apps": [{"authorName": "Tulip Author(s)", "categories": ["Multimedia"], "suggestedVersionCode": "2147483647", "license": "Unknown", "name": "Tulip", "summary": "Watch TV shows and movies online", "added": 1651623392000, "packageName": "com.tajmoti.tulip", "lastUpdated": 1651623395000}], "packages": {"com.tajmoti.tulip": [{"added": 1651623392000, "apkName": "app-arm64-v8a-release.apk", "hash": "9ccb6a4716373b44e971a2183b4c66bf550bd3afe5be7156376174e830b6d55b", "hashType": "sha256", "minSdkVersion": 21, "nativecode": ["arm64-v8a"], "packageName": "com.tajmoti.tulip", "sig": "a57bbb44a07b85a6d37e15e1cc65fb06", "signer": "9bd08c511359fd6f4dfe978ced43b64e921ae4ad25a01966e7438233ec03784f", "size": 23102040, "targetSdkVersion": 31, "uses-permission": [["android.permission.INTERNET", null], ["android.permission.ACCESS_NETWORK_STATE", null], ["android.permission.FOREGROUND_SERVICE", null]], "versionCode": 18, "versionName": "0.14.1"}, {"added": 1651623393000, "apkName": "app-armeabi-v7a-release.apk", "hash": "9ac420c5e5e644d3efb7b8af8e2bd6070cc29e2b24f6b34215ed443c4ca85c0c", "hashType": "sha256", "minSdkVersion": 21, "nativecode": ["armeabi-v7a"], "packageName": "com.tajmoti.tulip", "sig": "a57bbb44a07b85a6d37e15e1cc65fb06", "signer": "9bd08c511359fd6f4dfe978ced43b64e921ae4ad25a01966e7438233ec03784f", "size": 22774879, "targetSdkVersion": 31, "uses-permission": [["android.permission.INTERNET", null], ["android.permission.ACCESS_NETWORK_STATE", null], ["android.permission.FOREGROUND_SERVICE", null]], "versionCode": 18, "versionName": "0.14.1"}, {"added": 1651623394000, "apkName": "app-x86-release.apk", "hash": "746464aa91b3b55586cc2310db431a544d869f7469bbfa10bda7b7f26f4d0750", "hashType": "sha256", "minSdkVersion": 21, "nativecode": ["x86"], "packageName": "com.tajmoti.tulip", "sig": "a57bbb44a07b85a6d37e15e1cc65fb06", "signer": "9bd08c511359fd6f4dfe978ced43b64e921ae4ad25a01966e7438233ec03784f", "size": 24018913, "targetSdkVersion": 31, "uses-permission": [["android.permission.INTERNET", null], ["android.permission.ACCESS_NETWORK_STATE", null], ["android.permission.FOREGROUND_SERVICE", null]], "versionCode": 18, "versionName": "0.14.1"}, {"added": 1651623395000, "apkName": "app-x86_64-release.apk", "hash": "e16704be45e8c1c8781f8d4806749a5a56572538be6e9ea915972dabad7966c9", "hashType": "sha256", "minSdkVersion": 21, "nativecode": ["x86_64"], "packageName": "com.tajmoti.tulip", "sig": "a57bbb44a07b85a6d37e15e1cc65fb06", "signer": "9bd08c511359fd6f4dfe978ced43b64e921ae4ad25a01966e7438233ec03784f", "size": 24707754, "targetSdkVersion": 31, "uses-permission": [["android.permission.INTERNET", null], ["android.permission.ACCESS_NETWORK_STATE", null], ["android.permission.FOREGROUND_SERVICE", null]], "versionCode": 18, "versionName": "0.14.1"}]}}